fastapi_cloud_healthcheck_azure_vm/__init__.py
fastapi_cloud_healthcheck_azure_vm/service.py
fastapi_cloud_healthcheck_azure_vm-1.0.1.dist-info/LICENSE
fastapi_cloud_healthcheck_azure_vm-1.0.1.dist-info/METADATA
fastapi_cloud_healthcheck_azure_vm-1.0.1.dist-info/WHEEL
fastapi_cloud_healthcheck_azure_vm-1.0.1.dist-info/RECORD
