Metadata-Version: 2.1
Name: fastapi-cloud-healthcheck-azure-vm
Version: 1.0.1
Summary: This package is designed to validate the operational status of Azure Virtual Machines (VMs). It provides comprehensive diagnostics on the health of an Azure VM by checking its power state, disk health, and network interface status.
Home-page: https://github.com/yogeshselvarajan/fastapi_cloud_healthcheck_azure_vm
License: MIT
Keywords: fastapi,healthcheck,cloud,azure,vm,compute
Author: Yogesh Selvarajan
Author-email: yogeshselvarajan@gmail.com
Requires-Python: >=3.8,<4.0
Classifier: Framework :: FastAPI
Classifier: License :: OSI Approved :: MIT License
Classifier: Programming Language :: Python :: 3
Classifier: Programming Language :: Python :: 3.8
Classifier: Programming Language :: Python :: 3.9
Classifier: Programming Language :: Python :: 3.10
Classifier: Programming Language :: Python :: 3.11
Classifier: Programming Language :: Python :: 3.12
Requires-Dist: azure-identity (>=1.12.0,<2.0.0)
Requires-Dist: azure-mgmt-compute (>=26.0.0,<27.0.0)
Requires-Dist: azure-mgmt-network (>=25.0.0,<26.0.0)
Requires-Dist: fastapi_cloud_healthcheck (>=0.1.4,<0.2.0)
Project-URL: Repository, https://github.com/yogeshselvarajan/fastapi_cloud_healthcheck_azure_vm
